{"productCode":"PP048","name":"Serene","category1":"Writing Instruments","category2":"China Made Pens","category3":"On Sale","category4":null,"category5":null,"category6":null,"description":"Push action plastic pen, metallic coloured body with silver fittings and black dotty rubber grip, high quality German manufactured black ink refill, 1800 metres writing distance, tungsten carbide ball provides you with quality writing.","additionalInfo":null,"isOnSale":true,"isFreightFree":false,"isOverseasSourcing":false,"images":["PP048_1.jpg","PP048_2.jpg","PP048_3.jpg","PP048_4.jpg","PP048_5.jpg","PP048_6.jpg","PP048_7.jpg"],"productDisclaimer":"GST additional. Other additional charges may apply. We reserve the right to change prices and charges without notice. Please supply or email logo in vectorised format in an EPS or PDF File. Current stocked item style may vary slightly from image shown. If item style is paramount then please request sample of current shipment prior to ordering. Delievery time from Dex Group to client is not included. Days stated means working days from artwork approval to dispatch.","parts":[{"partName":null,"colours":["Black","Green","Red","Blue","Silver","Purple"],"length":"143","width":null,"height":"11"}],"printOptions":[{"printType":"Pad Print:","description":"45mmW x 7mmH (barrel)"}],"priceLists":[{"type":"local","blanks":[{"type":"local","description":"Local Blank Stock","prices":[{"qty":100,"unitPrice":0.64},{"qty":250,"unitPrice":0.46},{"qty":500,"unitPrice":0.34},{"qty":1000,"unitPrice":0.32},{"qty":2500,"unitPrice":0.31},{"qty":5000,"unitPrice":0.29},{"qty":10000,"unitPrice":0.28}]}],"services":[{"priceListType":"local","days":3,"serviceType":"3 Days Print Per Col/Pos","unitPrice":0.12,"Setup":30,"minOrderQty":100,"maxOrderQty":10000},{"priceListType":"local","days":7,"serviceType":"7 Days Print Per Col/Pos","unitPrice":0.08,"Setup":30,"minOrderQty":100,"maxOrderQty":10000},{"priceListType":"local","days":12,"serviceType":"12 Days Print Per Col/Pos","unitPrice":0.06,"Setup":30,"minOrderQty":100,"maxOrderQty":10000}]},{"type":"offshore","blanks":[{"type":"offshore","description":"28 Days Blank Stock","prices":[{"qty":100,"unitPrice":0.26},{"qty":250,"unitPrice":0.26},{"qty":500,"unitPrice":0.26},{"qty":1000,"unitPrice":0.26},{"qty":2500,"unitPrice":0.26},{"qty":5000,"unitPrice":0.26},{"qty":10000,"unitPrice":0.26}]}],"services":[{"priceListType":"offshore","days":28,"serviceType":"28 Days Print Per Col/Pos","unitPrice":0.04,"Setup":30,"minOrderQty":100,"maxOrderQty":10000}]}],"packing":{"description":"Loose packed or optional gift box/pouch available","cartonHeight":22,"cartonWidth":31,"cartonLength":53,"cartonQuantity":1000,"cartonWeight":16}}