{"productCode":"Opera B","name":"Opera B","category1":"Writing Instruments","category2":"Erga - Italian","category3":"Local Stock","category4":null,"category5":null,"category6":null,"description":"ERGA® – Italian Top Quality Pens -- Since 1968. Great....Classic! A design that provides large clip to get always top visible printings, retractable ballpoint pen, nontoxic ABS and nontoxic Terlux, solid shiny clip, solid matt barrel, high quality Germany black ink refill with tungsten carbide ball, 2000m.","additionalInfo":"Italian Design and Make. Exclusive to Dex Collection in Australia and New Zealand.","isOnSale":false,"isFreightFree":true,"isOverseasSourcing":false,"images":[""],"productDisclaimer":"GST additional. Other additional charges may apply. We reserve the right to change prices and charges without notice. Please supply or email logo in vectorised format in an EPS or PDF File. Current stocked item style may vary slightly from image shown. If item style is paramount then please request sample of current shipment prior to ordering. Delievery time from Dex Group to client is not included. Days stated means working days from artwork approval to dispatch.","parts":[{"partName":null,"colours":["White","Black","Red","Dark Blue","Green"],"length":"141","width":"11","height":"16"}],"printOptions":[{"printType":"Pad Print:","description":"55mmW x 7mmH (barrel), 33mmW x 6mmH (clip)"},{"printType":"Direct Digital:","description":"55mmW x 7mmH (barrel), 33mmW x 6mmH (clip)"}],"priceLists":[{"type":"local","blanks":[{"type":"local","description":"Local Blank Stock","prices":[{"qty":100,"unitPrice":0.4},{"qty":250,"unitPrice":0.35},{"qty":500,"unitPrice":0.26},{"qty":1000,"unitPrice":0.25},{"qty":2500,"unitPrice":0.23},{"qty":5000,"unitPrice":0.21},{"qty":10000,"unitPrice":0.2}]}],"services":[{"priceListType":"local","days":1,"serviceType":"24 Hrs. Direct Digital Per Pos\r\n\r\n, Add","unitPrice":0.3,"Setup":30,"minOrderQty":100,"maxOrderQty":10000},{"priceListType":"local","days":3,"serviceType":"3 Days Print Per Col/Pos\r\n\r\n, Add","unitPrice":0.12,"Setup":30,"minOrderQty":100,"maxOrderQty":5000},{"priceListType":"local","days":3,"serviceType":"3 Days Direct Digital Per Pos\r\n\r\n, Add","unitPrice":0.24,"Setup":30,"minOrderQty":100,"maxOrderQty":10000},{"priceListType":"local","days":7,"serviceType":"7 Days Print Per Col/Pos\r\n\r\n, Add","unitPrice":0.1,"Setup":30,"minOrderQty":100,"maxOrderQty":10000},{"priceListType":"local","days":7,"serviceType":"7 Days Direct Digital Per Pos\r\n\r\n, Add","unitPrice":0.2,"Setup":30,"minOrderQty":100,"maxOrderQty":10000},{"priceListType":"local","days":12,"serviceType":"12 Days Print Per Col/Pos\r\n\r\n, Add","unitPrice":0.08,"Setup":30,"minOrderQty":100,"maxOrderQty":10000},{"priceListType":"local","days":12,"serviceType":"12 Days Direct Digital Per Pos\r\n\r\n, Add","unitPrice":0.18,"Setup":30,"minOrderQty":100,"maxOrderQty":10000}]}],"packing":{"description":"Loose packed","cartonHeight":17,"cartonWidth":48,"cartonLength":31,"cartonQuantity":1000,"cartonWeight":8.4}}